{"name":"rblas","counts":{"deprecated":0,"experimental":13,"unstable":248,"stable":9,"frozen":0,"locked":0,"unmarked":12},"submodules":[{"name":"attribute","counts":{"deprecated":0,"experimental":5,"unstable":0,"stable":6,"frozen":0,"locked":0,"unmarked":11},"submodules":[]},{"name":"matrix","counts":{"deprecated":0,"experimental":0,"unstable":61,"stable":1,"frozen":0,"locked":0,"unmarked":0},"submodules":[{"name":"ll","counts":{"deprecated":0,"experimental":0,"unstable":30,"stable":1,"frozen":0,"locked":0,"unmarked":0},"submodules":[]},{"name":"ops","counts":{"deprecated":0,"experimental":0,"unstable":19,"stable":0,"frozen":0,"locked":0,"unmarked":0},"submodules":[]}]},{"name":"matrix_vector","counts":{"deprecated":0,"experimental":0,"unstable":114,"stable":1,"frozen":0,"locked":0,"unmarked":0},"submodules":[{"name":"ll","counts":{"deprecated":0,"experimental":0,"unstable":68,"stable":1,"frozen":0,"locked":0,"unmarked":0},"submodules":[]},{"name":"ops","counts":{"deprecated":0,"experimental":0,"unstable":45,"stable":0,"frozen":0,"locked":0,"unmarked":0},"submodules":[]}]},{"name":"vector","counts":{"deprecated":0,"experimental":8,"unstable":73,"stable":1,"frozen":0,"locked":0,"unmarked":0},"submodules":[{"name":"ll","counts":{"deprecated":0,"experimental":0,"unstable":46,"stable":1,"frozen":0,"locked":0,"unmarked":0},"submodules":[]},{"name":"ops","counts":{"deprecated":0,"experimental":0,"unstable":21,"stable":0,"frozen":0,"locked":0,"unmarked":0},"submodules":[]}]}]}